ynabmemoparser/__init__.py
ynabmemoparser/parser.py
ynabmemoparser/recordbuilder.py
ynabmemoparser/ynabmemoparser.py
ynabmemoparser/ynabrecord.py
ynab_memo_parser-0.1.0.dist-info/LICENSE
ynab_memo_parser-0.1.0.dist-info/METADATA
ynab_memo_parser-0.1.0.dist-info/WHEEL
ynab_memo_parser-0.1.0.dist-info/RECORD
