Metadata-Version: 2.1
Name: ynab-memo-parser
Version: 0.1.0
Summary: Library to parse & update memo and/or payee information in YNAB transactions
License: MIT
Author: Daniel Basta
Author-email: ynab@basta.info
Requires-Python: >=3.8,<4.0
Classifier: License :: OSI Approved :: MIT License
Classifier: Operating System :: OS Independent
Classifier: Programming Language :: Python :: 3
Classifier: Programming Language :: Python :: 3.8
Classifier: Programming Language :: Python :: 3.9
Classifier: Programming Language :: Python :: 3.10
Classifier: Programming Language :: Python :: 3.11
Classifier: Programming Language :: Python :: 3.12
Requires-Dist: pytest (>=8.0.2,<9.0.0)
Requires-Dist: requests (>=2.28.0)
